Workbook

Sheet Read Me
A1: Stantec Inc. (TSX/NYSE: STN) — Forecast & DCF Model
A2: C$ millions unless stated. Built to follow the Stantec Build Guide, step by step.
A4: Legend
A5: 1234.5 | B5: Blue = number typed in (from a report, or your assumption)
A6: 1234.5 | B6: Black = formula (don't type over it)
A7: 1234.5 | B7: Green = link pulled from another tab
B8: Yellow = you fill this in
A10: How to type numbers
A11: 8144.2 | B11: Example: gross revenue of $8,144.2 million is typed as 8144.2
A12: 0.24 | B12: Percentages: type 24% (Excel stores it as 0.24)
A13: Costs | B13: Type costs and cash outflows (capex, dividends) as positive numbers; formulas subtract them
A15: Order of work
A16: 1. Historicals | B16: FY2024–25 income statement is already entered from the results release. Fill the yellow cells: the FY2023 column, plus the balance sheet and cash flow. FY2025 balance sheet is required; the rest is for ratios. The Check row must read 0.
A17: 2. Ratios | B17: Automatic. Compare FY2025 with the build guide.
A18: 3. Assumptions | B18: Review the base case. Fill the 3 yellow market inputs: 10-year Government of Canada yield, beta (Yahoo Finance, STN.TO), today's share price.
A19: 4. Forecast | B19: Automatic. FY2026 should match the guide's check column.
A20: 5. WACC | B20: Automatic once market inputs are in. Expect roughly 8–9.5%.
A21: 6. DCF | B21: Automatic, including the sensitivity table (build guide Step 7 is already done).
A22: 7. Comps | B22: Fill EV/EBITDA for the four peers and Stantec, and Stantec's EBITDA, all from the same source.
A23: 8. Summary | B23: Add your name and date, check the verdict, and edit the bullets in your own words. Export this tab to PDF.
A25: Sources
B26: Stantec Q4 and full-year 2025 results release (Feb 25, 2026): investors.stantec.com
B27: Stantec 2025 and 2024 Annual Reports: stantec.com (Investors), SEDAR+ (sedarplus.ca), or SEC EDGAR

Sheet Historicals
A1: Historical Financials
A2: C$ millions, fiscal years ending December 31
A3: Income statement | B3: FY2023 | C3: FY2024 | D3: FY2025 | E3: Source / notes
A4: Gross revenue | B4: 6479.6 | C4: 7500 | D4: 8144.2 | E4: FY2024–25: Stantec Q4/FY2025 results release (Feb 25, 2026), Financial Summary table. FY2023: 2024 Annual Report.
A5: Subconsultant and other direct expenses | B5: 1413.4 | C5: 1633.4 | D5: 1649.4 | E5: FY2024–25 derived as gross − net revenue from the release; confirm against the annual report line.
A6: Net revenue | B6: =B4-B5 -> 5066.2 | C6: =C4-C5 -> 5866.6 | D6: =D4-D5 -> 6494.8 | E6: Stantec measures growth and margins on this line
A7: Direct payroll costs | B7: 2321.5 | C7: 2670.9 | D7: 2965.8 | E7: FY2024–25: Stantec Q4/FY2025 results release (Feb 25, 2026), Financial Summary table. FY2023: 2024 Annual Report.
A8: Project margin | B8: =B6-B7 -> 2744.7 | C8: =C6-C7 -> 3195.7 | D8: =D6-D7 -> 3529
A9: Administrative and marketing | B9: 1965.3 | C9: 2286.1 | D9: 2457.5 | E9: FY2024–25: Stantec Q4/FY2025 results release (Feb 25, 2026), Financial Summary table. FY2023: 2024 Annual Report.
A10: Depreciation of property and equipment | B10: 59.9 | C10: 67.7 | D10: 70.6 | E10: FY2024–25: Stantec Q4/FY2025 results release (Feb 25, 2026), Financial Summary table. FY2023: 2024 Annual Report.
A11: Depreciation of lease assets | B11: 121.7 | C11: 127.1 | D11: 133.6 | E11: FY2024–25: Stantec Q4/FY2025 results release (Feb 25, 2026), Financial Summary table. FY2023: 2024 Annual Report.
A12: Net impairment | B12: 0.3 | C12: 34.9 | D12: 6 | E12: FY2024–25: Stantec Q4/FY2025 results release (Feb 25, 2026), Financial Summary table. FY2023: 2024 Annual Report.
A13: Amortization of intangible assets | B13: 102 | C13: 123.8 | D13: 147.5 | E13: FY2024–25: Stantec Q4/FY2025 results release (Feb 25, 2026), Financial Summary table. FY2023: 2024 Annual Report.
A14: EBIT (operating profit) | B14: =B8-SUM(B9:B13) -> 495.5 | C14: =C8-SUM(C9:C13) -> 556.1 | D14: =D8-SUM(D9:D13) -> 713.8
A15: Net interest and finance expense | B15: 93 | C15: 104.4 | D15: 102 | E15: FY2024–25: Stantec Q4/FY2025 results release (Feb 25, 2026), Financial Summary table. FY2023: 2024 Annual Report.
A16: Other income | B16: 5.2 | C16: 13.6 | D16: 18.2 | E16: FY2024–25: Stantec Q4/FY2025 results release (Feb 25, 2026), Financial Summary table. FY2023: 2024 Annual Report.
A17: Income before taxes | B17: =B14-B15+B16 -> 407.7 | C17: =C14-C15+C16 -> 465.3 | D17: =D14-D15+D16 -> 630
A18: Income taxes | B18: 91.2 | C18: 103.8 | D18: 150.6 | E18: FY2024–25: Stantec Q4/FY2025 results release (Feb 25, 2026), Financial Summary table. FY2023: 2024 Annual Report.
A19: Net income | B19: =B17-B18 -> 316.5 | C19: =C17-C18 -> 361.5 | D19: =D17-D18 -> 479.4
A20: Reported net income | B20: 316.5 | C20: 361.5 | D20: 479.4 | E20: Type the net income shown in the report
A21: Check (must be 0) | B21: =B19-B20 -> 0 | C21: =C19-C20 -> 0 | D21: =D19-D20 -> 0 | E21: Not 0 = a mistyped number or a missing line
A23: Balance sheet (Dec 31) | B23: FY2023 | C23: FY2024 | D23: FY2025
A24: Cash and cash equivalents | B24: 352.9 | C24: 228.5 | D24: 398.1 | E24: FY2025 required (used in net debt and the DCF)
A25: Trade and other receivables | B25: 1323.8 | C25: 1323.8 | D25: 1306.5 | E25: FY2025 required (drives working capital %)
A26: Contract assets (work done, not yet billed) | B26: 712.6 | C26: 840.5 | D26: 872.8 | E26: FY2025 required
A27: Trade and other payables | B27: 842.4 | C27: 1018.7 | D27: 1125.3 | E27: FY2025 required
A28: Contract liabilities (billed, not yet done) | B28: 397.5 | C28: 502.4 | D28: 581.7 | E28: FY2025 required
A29: Total debt (excl. lease liabilities) | B29: 1098.2 | C29: 1383.5 | D29: 1818.3 | E29: FY2024–25: "Total long-term debt" from the results release. Confirm it includes the current portion and excludes leases.
A30: Total shareholders' equity | B30: 2451.1 | C30: 2945.1 | D30: 3240.4 | E30: Used for return on equity
A32: Cash flow | B32: FY2023 | C32: FY2024 | D32: FY2025
A33: Cash flows from operating activities | B33: 520 | C33: 603.1 | D33: 862.9 | E33: FY2024–25: Stantec Q4/FY2025 results release (Feb 25, 2026), Financial Summary table. FY2023: 2024 Annual Report.
A34: Capex (property & equipment + intangibles) | B34: 100.6 | C34: 99 | D34: 71.9 | E34: Type as a positive number
A35: Business acquisitions | B35: 75.6 | C35: 555 | D35: 454 | E35: Type as a positive number
A36: Dividends paid | B36: 84.9 | C36: 94 | D36: 101 | E36: Type as a positive number

Sheet Ratios
A1: Key Ratios
A2: All automatic. FY2025 should match the build guide.
A3: Ratio | B3: FY2023 | C3: FY2024 | D3: FY2025 | E3: Formula
A4: Net revenue growth | B4: n/a | C4: =IF(Historicals!B6=0,0,Historicals!C6/Historicals!B6-1) -> 0.15798824 | D4: =IF(Historicals!C6=0,0,Historicals!D6/Historicals!C6-1) -> 0.10708076 | E4: (this year − last year) ÷ last year
A5: Project margin % | B5: =IF(Historicals!B6=0,0,Historicals!B8/Historicals!B6) -> 0.541767 | C5: =IF(Historicals!C6=0,0,Historicals!C8/Historicals!C6) -> 0.54472778 | D5: =IF(Historicals!D6=0,0,Historicals!D8/Historicals!D6) -> 0.54335776 | E5: project margin ÷ net revenue
A6: Admin & marketing % | B6: =IF(Historicals!B6=0,0,Historicals!B9/Historicals!B6) -> 0.38792389 | C6: =IF(Historicals!C6=0,0,Historicals!C9/Historicals!C6) -> 0.38968056 | D6: =IF(Historicals!D6=0,0,Historicals!D9/Historicals!D6) -> 0.37837963 | E6: admin & marketing ÷ net revenue
A7: Depreciation of P&E % | B7: =IF(Historicals!B6=0,0,Historicals!B10/Historicals!B6) -> 0.011823457 | C7: =IF(Historicals!C6=0,0,Historicals!C10/Historicals!C6) -> 0.011539904 | D7: =IF(Historicals!D6=0,0,Historicals!D10/Historicals!D6) -> 0.010870235 | E7: ÷ net revenue
A8: Depreciation of lease assets % | B8: =IF(Historicals!B6=0,0,Historicals!B11/Historicals!B6) -> 0.024021949 | C8: =IF(Historicals!C6=0,0,Historicals!C11/Historicals!C6) -> 0.021665019 | D8: =IF(Historicals!D6=0,0,Historicals!D11/Historicals!D6) -> 0.020570302 | E8: ÷ net revenue
A9: Amortization % | B9: =IF(Historicals!B6=0,0,Historicals!B13/Historicals!B6) -> 0.020133433 | C9: =IF(Historicals!C6=0,0,Historicals!C13/Historicals!C6) -> 0.021102513 | D9: =IF(Historicals!D6=0,0,Historicals!D13/Historicals!D6) -> 0.022710476 | E9: ÷ net revenue
A10: EBIT margin | B10: =IF(Historicals!B6=0,0,Historicals!B14/Historicals!B6) -> 0.097805061 | C10: =IF(Historicals!C6=0,0,Historicals!C14/Historicals!C6) -> 0.09479085 | D10: =IF(Historicals!D6=0,0,Historicals!D14/Historicals!D6) -> 0.10990331 | E10: EBIT ÷ net revenue
A11: EBITDA ($mm) | B11: =Historicals!B14+Historicals!B10+Historicals!B13 -> 657.4 | C11: =Historicals!C14+Historicals!C10+Historicals!C13 -> 747.6 | D11: =Historicals!D14+Historicals!D10+Historicals!D13 -> 931.9 | E11: EBIT + depreciation of P&E + amortization (leases treated as rent)
A12: EBITDA margin | B12: =IF(Historicals!B6=0,0,B11/Historicals!B6) -> 0.12976195 | C12: =IF(Historicals!C6=0,0,C11/Historicals!C6) -> 0.12743327 | D12: =IF(Historicals!D6=0,0,D11/Historicals!D6) -> 0.14348402 | E12: EBITDA ÷ net revenue
A13: Net income margin | B13: =IF(Historicals!B6=0,0,Historicals!B19/Historicals!B6) -> 0.062472859 | C13: =IF(Historicals!C6=0,0,Historicals!C19/Historicals!C6) -> 0.061620018 | D13: =IF(Historicals!D6=0,0,Historicals!D19/Historicals!D6) -> 0.073812896 | E13: net income ÷ net revenue
A14: Effective tax rate | B14: =IF(Historicals!B17=0,0,Historicals!B18/Historicals!B17) -> 0.22369389 | C14: =IF(Historicals!C17=0,0,Historicals!C18/Historicals!C17) -> 0.22308188 | D14: =IF(Historicals!D17=0,0,Historicals!D18/Historicals!D17) -> 0.23904762 | E14: income taxes ÷ income before taxes
A15: Capex % of net revenue | B15: =IF(Historicals!B6=0,0,Historicals!B34/Historicals!B6) -> 0.019857092 | C15: =IF(Historicals!C6=0,0,Historicals!C34/Historicals!C6) -> 0.016875192 | D15: =IF(Historicals!D6=0,0,Historicals!D34/Historicals!D6) -> 0.011070395 | E15: capex ÷ net revenue
A16: Cash conversion | B16: =IF(Historicals!B19=0,0,Historicals!B33/Historicals!B19) -> 1.64297 | C16: =IF(Historicals!C19=0,0,Historicals!C33/Historicals!C19) -> 1.6683264 | D16: =IF(Historicals!D19=0,0,Historicals!D33/Historicals!D19) -> 1.7999583 | E16: operating cash flow ÷ net income
A17: Net debt ($mm) | B17: =Historicals!B29-Historicals!B24 -> 745.3 | C17: =Historicals!C29-Historicals!C24 -> 1155 | D17: =Historicals!D29-Historicals!D24 -> 1420.2 | E17: debt − cash (no leases)
A18: Net debt ÷ EBITDA | B18: =IF(B11=0,0,B17/B11) -> 1.1337085 | C18: =IF(C11=0,0,C17/C11) -> 1.5449438 | D18: =IF(D11=0,0,D17/D11) -> 1.5239833 | E18: under 2x is comfortable
A19: Days sales outstanding | B19: =IF(Historicals!B4=0,0,(Historicals!B25+Historicals!B26-Historicals!B28)/Historicals!B4*365) -> 92.320282 | C19: =IF(Historicals!C4=0,0,(Historicals!C25+Historicals!C26-Historicals!C28)/Historicals!C4*365) -> 80.879133 | D19: =IF(Historicals!D4=0,0,(Historicals!D25+Historicals!D26-Historicals!D28)/Historicals!D4*365) -> 71.599912 | E19: (receivables + contract assets − contract liabilities) ÷ gross revenue × 365; Stantec reported 69 for 2025
A20: Net working capital ($mm) | B20: =Historicals!B25+Historicals!B26-Historicals!B27-Historicals!B28 -> 796.5 | C20: =Historicals!C25+Historicals!C26-Historicals!C27-Historicals!C28 -> 643.2 | D20: =Historicals!D25+Historicals!D26-Historicals!D27-Historicals!D28 -> 472.3 | E20: receivables + contract assets − payables − contract liabilities
A21: Net working capital % of net revenue | B21: =IF(Historicals!B6=0,0,B20/Historicals!B6) -> 0.15721843 | C21: =IF(Historicals!C6=0,0,C20/Historicals!C6) -> 0.10963761 | D21: =IF(Historicals!D6=0,0,D20/Historicals!D6) -> 0.072719714 | E21: FY2025 value feeds the forecast
A22: Return on equity | B22: n/a | C22: =IF((Historicals!B30+Historicals!C30)=0,0,Historicals!C19/((Historicals!B30+Historicals!C30)/2)) -> 0.13398317 | D22: =IF((Historicals!C30+Historicals!D30)=0,0,Historicals!D19/((Historicals!C30+Historicals!D30)/2)) -> 0.15500768 | E22: net income ÷ average equity

Sheet Assumptions
A1: Forecast Assumptions — Base Case
A2: Change a blue cell and the whole model updates. Percentages are % of net revenue unless noted.
A3: Assumption | B3: FY2026 | C3: FY2027 | D3: FY2028 | E3: FY2029 | F3: FY2030 | G3: Why
A4: Net revenue growth | B4: 0.1 | C4: 0.08 | D4: 0.07 | E4: 0.06 | F4: 0.05 | G4: 2026 = midpoint of management's 8.5–11.5% guidance; fades to a long-run rate. No new acquisitions (same as guidance).
A5: Project margin % | B5: 0.543 | C5: =B5 -> 0.543 | D5: =C5 -> 0.543 | E5: =D5 -> 0.543 | F5: =E5 -> 0.543 | G5: The 2025 level; has held in a 54–55% band.
A6: Admin & marketing % | B6: 0.375 | C6: =B6 -> 0.375 | D6: =C6 -> 0.375 | E6: =D6 -> 0.375 | F6: =E6 -> 0.375 | G6: Fell from 39.0% (2024) to 37.8% (2025); assumes a little more cost discipline, then holds.
A7: Depreciation of P&E % | B7: 0.011 | C7: =B7 -> 0.011 | D7: =C7 -> 0.011 | E7: =D7 -> 0.011 | F7: =E7 -> 0.011 | G7: The 2025 level.
A8: Depreciation of lease assets % | B8: 0.02 | C8: =B8 -> 0.02 | D8: =C8 -> 0.02 | E8: =D8 -> 0.02 | F8: =E8 -> 0.02 | G8: The 2025 level (about 2.1%).
A9: Amortization of intangibles % | B9: 0.023 | C9: =B9 -> 0.023 | D9: =C9 -> 0.023 | E9: =D9 -> 0.023 | F9: =E9 -> 0.023 | G9: The 2025 level; conservative, since it would shrink without new acquisitions.
A10: Tax rate (on EBIT) | B10: 0.24 | C10: =B10 -> 0.24 | D10: =C10 -> 0.24 | E10: =D10 -> 0.24 | F10: =E10 -> 0.24 | G10: Midpoint of management's 23–25% guidance; 2025 was 23.9%.
A11: Capex % of net revenue | B11: 0.016 | C11: =B11 -> 0.016 | D11: =C11 -> 0.016 | E11: =D11 -> 0.016 | F11: =E11 -> 0.016 | G11: Midpoint of management's 1.4–1.8% guidance.
A12: Net working capital % of net revenue | B12: =Ratios!D21 -> 0.072719714 | C12: =B12 -> 0.072719714 | D12: =C12 -> 0.072719714 | E12: =D12 -> 0.072719714 | F12: =E12 -> 0.072719714 | G12: From your FY2025 balance sheet (Ratios tab); held flat. Shows "-" until the balance sheet is filled in.
A14: Valuation inputs | B14: Value | G14: Why / where to find it
A15: Terminal growth (g) | B15: 0.025 | G15: Long-run growth after 2030: roughly inflation plus a little. Must stay below WACC.
A16: Equity risk premium | B16: 0.055 | G16: Extra return investors demand for stocks over bonds; a common assumption.
A17: Pre-tax cost of debt | B17: 0.05 | G17: Placeholder. Replace with the average rate on Stantec's notes (debt note in the annual report) if you find it.
A18: Diluted shares (millions) | B18: 114.1 | G18: Weighted average diluted shares: 114,066,995 (results release, Feb 25, 2026).
A19: Market inputs — fill in today's values | B19: Value | G19: Where to find it
A20: Risk-free rate | B20: 0.0395 | G20: Government of Canada 10-year bond yield (Bank of Canada website). Type as %, e.g. 3.2%.
A21: Beta | B21: 0.72 | G21: Yahoo Finance, ticker STN.TO, Statistics tab: "Beta (5Y Monthly)".
A22: Current share price (C$) | B22: 96.25 | G22: Yahoo Finance, ticker STN.TO.

Sheet Forecast
A1: Forecast to Unlevered Free Cash Flow
A2: C$ millions. FY2025 = actual (linked); FY2026–2030 = formulas driven by the Assumptions tab.
A3: Line | B3: FY2025A | C3: FY2026E | D3: FY2027E | E3: FY2028E | F3: FY2029E | G3: FY2030E
A4: Net revenue growth | B4: =Ratios!D4 -> 0.10708076 | C4: =Assumptions!B4 -> 0.1 | D4: =Assumptions!C4 -> 0.08 | E4: =Assumptions!D4 -> 0.07 | F4: =Assumptions!E4 -> 0.06 | G4: =Assumptions!F4 -> 0.05
A5: Net revenue | B5: =Historicals!D6 -> 6494.8 | C5: =B5*(1+C4) -> 7144.28 | D5: =C5*(1+D4) -> 7715.8224 | E5: =D5*(1+E4) -> 8255.93 | F5: =E5*(1+F4) -> 8751.2858 | G5: =F5*(1+G4) -> 9188.8501
A6: Project margin | B6: =Historicals!D8 -> 3529 | C6: =C5*Assumptions!B5 -> 3879.344 | D6: =D5*Assumptions!C5 -> 4189.6916 | E6: =E5*Assumptions!D5 -> 4482.97 | F6: =F5*Assumptions!E5 -> 4751.9482 | G6: =G5*Assumptions!F5 -> 4989.5456
A7: Administrative and marketing | B7: =Historicals!D9 -> 2457.5 | C7: =C5*Assumptions!B6 -> 2679.105 | D7: =D5*Assumptions!C6 -> 2893.4334 | E7: =E5*Assumptions!D6 -> 3095.9737 | F7: =F5*Assumptions!E6 -> 3281.7322 | G7: =G5*Assumptions!F6 -> 3445.8188
A8: Depreciation of property and equipment | B8: =Historicals!D10 -> 70.6 | C8: =C5*Assumptions!B7 -> 78.58708 | D8: =D5*Assumptions!C7 -> 84.874046 | E8: =E5*Assumptions!D7 -> 90.81523 | F8: =F5*Assumptions!E7 -> 96.264143 | G8: =G5*Assumptions!F7 -> 101.07735
A9: Depreciation of lease assets | B9: =Historicals!D11 -> 133.6 | C9: =C5*Assumptions!B8 -> 142.8856 | D9: =D5*Assumptions!C8 -> 154.31645 | E9: =E5*Assumptions!D8 -> 165.1186 | F9: =F5*Assumptions!E8 -> 175.02572 | G9: =G5*Assumptions!F8 -> 183.777
A10: Amortization of intangible assets | B10: =Historicals!D13 -> 147.5 | C10: =C5*Assumptions!B9 -> 164.31844 | D10: =D5*Assumptions!C9 -> 177.46392 | E10: =E5*Assumptions!D9 -> 189.88639 | F10: =F5*Assumptions!E9 -> 201.27957 | G10: =G5*Assumptions!F9 -> 211.34355
A11: Net impairment (one-off, not forecast) | B11: =Historicals!D12 -> 6 | C11: 0 | D11: 0 | E11: 0 | F11: 0 | G11: 0
A12: EBIT | B12: =B6-B7-B8-B9-B10-B11 -> 713.8 | C12: =C6-C7-C8-C9-C10-C11 -> 814.44792 | D12: =D6-D7-D8-D9-D10-D11 -> 879.60375 | E12: =E6-E7-E8-E9-E10-E11 -> 941.17602 | F12: =F6-F7-F8-F9-F10-F11 -> 997.64658 | G12: =G6-G7-G8-G9-G10-G11 -> 1047.5289
A13: EBIT margin | B13: =IF(B5=0,0,B12/B5) -> 0.10990331 | C13: =IF(C5=0,0,C12/C5) -> 0.114 | D13: =IF(D5=0,0,D12/D5) -> 0.114 | E13: =IF(E5=0,0,E12/E5) -> 0.114 | F13: =IF(F5=0,0,F12/F5) -> 0.114 | G13: =IF(G5=0,0,G12/G5) -> 0.114
A14: Tax on EBIT | C14: =C12*Assumptions!B10 -> 195.4675 | D14: =D12*Assumptions!C10 -> 211.1049 | E14: =E12*Assumptions!D10 -> 225.88224 | F14: =F12*Assumptions!E10 -> 239.43518 | G14: =G12*Assumptions!F10 -> 251.40694
A15: NOPAT (after-tax operating profit) | C15: =C12-C14 -> 618.98042 | D15: =D12-D14 -> 668.49885 | E15: =E12-E14 -> 715.29377 | F15: =F12-F14 -> 758.2114 | G15: =G12-G14 -> 796.12197
A16: Plus: depreciation of P&E + amortization | C16: =C8+C10 -> 242.90552 | D16: =D8+D10 -> 262.33796 | E16: =E8+E10 -> 280.70162 | F16: =F8+F10 -> 297.54372 | G16: =G8+G10 -> 312.4209
A17: Less: capex | C17: =C5*Assumptions!B11 -> 114.30848 | D17: =D5*Assumptions!C11 -> 123.45316 | E17: =E5*Assumptions!D11 -> 132.09488 | F17: =F5*Assumptions!E11 -> 140.02057 | G17: =G5*Assumptions!F11 -> 147.0216
A18: Less: increase in working capital | C18: =Assumptions!B12*(C5-B5) -> 47.23 | D18: =Assumptions!C12*(D5-C5) -> 41.5624 | E18: =Assumptions!D12*(E5-D5) -> 39.276468 | F18: =Assumptions!E12*(F5-E5) -> 36.022132 | G18: =Assumptions!F12*(G5-F5) -> 31.81955
A19: Unlevered free cash flow | C19: =C15+C16-C17-C18 -> 700.34746 | D19: =D15+D16-D17-D18 -> 765.82126 | E19: =E15+E16-E17-E18 -> 824.62404 | F19: =F15+F16-F17-F18 -> 879.71241 | G19: =G15+G16-G17-G18 -> 929.70172
A21: Leases are treated as rent: lease depreciation stays a cost and is NOT added back, and lease liabilities are left out of debt.

Sheet WACC
A1: Discount Rate (WACC)
A2: WACC = equity weight × cost of equity + debt weight × cost of debt × (1 − tax rate)
A3: Input | B3: Value | C3: Notes
A4: Risk-free rate | B4: =Assumptions!B20 -> 0.0395 | C4: Assumptions tab
A5: Beta | B5: =Assumptions!B21 -> 0.72 | C5: Assumptions tab
A6: Equity risk premium | B6: =Assumptions!B16 -> 0.055 | C6: Assumptions tab
A7: Cost of equity | B7: =B4+B5*B6 -> 0.0791 | C7: CAPM: safe return + beta × extra return for risk
A8: Pre-tax cost of debt | B8: =Assumptions!B17 -> 0.05 | C8: Assumptions tab
A9: Tax rate | B9: =Assumptions!B10 -> 0.24 | C9: Assumptions tab
A10: After-tax cost of debt | B10: =B8*(1-B9) -> 0.038 | C10: Interest is tax-deductible, so debt costs less after tax
A11: Share price (C$) | B11: =Assumptions!B22 -> 96.25 | C11: Assumptions tab
A12: Diluted shares (millions) | B12: =Assumptions!B18 -> 114.1 | C12: Assumptions tab
A13: Equity value (market cap) | B13: =B11*B12 -> 10982.125 | C13: share price × shares
A14: Debt (excl. leases) | B14: =Historicals!D29 -> 1818.3 | C14: Historicals, FY2025
A15: Total capital | B15: =B13+B14 -> 12800.425
A16: Equity weight | B16: =IF(B15=0,0,B13/B15) -> 0.85795003
A17: Debt weight | B17: =IF(B15=0,0,B14/B15) -> 0.14204997
A18: WACC | B18: =IF(OR(B4=0,B5=0,B11=0),0,B16*B7+B17*B10) -> 0.073261746 | C18: Shows "-" until the market inputs are filled in

Sheet DCF
A1: DCF Valuation
A2: Values Stantec as of Dec 31, 2025, with each year's cash arriving at year-end.
A3: Inputs | B3: Value
A4: WACC | B4: =WACC!B18 -> 0.073261746
A5: Terminal growth (g) | B5: =Assumptions!B15 -> 0.025
A6: Debt (excl. leases) | B6: =Historicals!D29 -> 1818.3
A7: Cash | B7: =Historicals!D24 -> 398.1
A8: Diluted shares (millions) | B8: =Assumptions!B18 -> 114.1
A9: Current share price (C$) | B9: =Assumptions!B22 -> 96.25
A11: Discounting | C11: FY2026E | D11: FY2027E | E11: FY2028E | F11: FY2029E | G11: FY2030E
A12: Year number | C12: 1 | D12: 2 | E12: 3 | F12: 4 | G12: 5
A13: Unlevered free cash flow | C13: =Forecast!C19 -> 700.34746 | D13: =Forecast!D19 -> 765.82126 | E13: =Forecast!E19 -> 824.62404 | F13: =Forecast!F19 -> 879.71241 | G13: =Forecast!G19 -> 929.70172
A14: Discount factor = 1 ÷ (1 + WACC)^year | C14: =1/(1+$B$4)^C12 -> 0.93173916 | D14: =1/(1+$B$4)^D12 -> 0.86813787 | E14: =1/(1+$B$4)^E12 -> 0.80887805 | F14: =1/(1+$B$4)^F12 -> 0.75366335 | G14: =1/(1+$B$4)^G12 -> 0.70221766
A15: PV of free cash flow | C15: =C13*C14 -> 652.54115 | D15: =D13*D14 -> 664.83843 | E15: =E13*E14 -> 667.02029 | F15: =F13*F14 -> 663.00701 | G15: =G13*G14 -> 652.85297
A17: Valuation | B17: Value | C17: Notes
A18: Sum of PV of free cash flows | B18: =SUM(C15:G15) -> 3300.2598
A19: Terminal value (at 2030) | B19: =IF($B$4<=$B$5,0,G13*(1+$B$5)/($B$4-$B$5)) -> 19745.333 | C19: FCF 2030 × (1 + g) ÷ (WACC − g)
A20: PV of terminal value | B20: =B19*G14 -> 13865.522 | C20: shrunk back five years
A21: Enterprise value | B21: =IF($B$4<=$B$5,0,B18+B20) -> 17165.782 | C21: value of the whole business
A22: Less: debt | B22: =B6 -> 1818.3
A23: Plus: cash | B23: =B7 -> 398.1
A24: Equity value | B24: =IF(B21=0,0,B21-B22+B23) -> 15745.582
A25: Value per share (C$) | B25: =IF(B8=0,0,B24/B8) -> 137.99809
A26: Current share price (C$) | B26: =B9 -> 96.25
A27: Upside / (downside) | B27: =IF(OR(B9=0,B25=0),0,B25/B9-1) -> 0.43374635
A28: Terminal value as % of EV | B28: =IF(B21=0,0,B20/B21) -> 0.80774194 | C28: usually 60–80% for a steady company
A30: Sensitivity: value per share (C$) | B30: WACC ↓ g → | C30: 0.02 | D30: 0.025 | E30: 0.03
B31: 0.075 | C31: =IF($B31<=C$30,0,(SUMPRODUCT($C$13:$G$13/(1+$B31)^$C$12:$G$12)+$G$13*(1+C$30)/($B31-C$30)/(1+$B31)^$G$12-$B$6+$B$7)/$B$8) -> 121.59483 | D31: =IF($B31<=D$30,0,(SUMPRODUCT($C$13:$G$13/(1+$B31)^$C$12:$G$12)+$G$13*(1+D$30)/($B31-D$30)/(1+$B31)^$G$12-$B$6+$B$7)/$B$8) -> 132.68815 | E31: =IF($B31<=E$30,0,(SUMPRODUCT($C$13:$G$13/(1+$B31)^$C$12:$G$12)+$G$13*(1+E$30)/($B31-E$30)/(1+$B31)^$G$12-$B$6+$B$7)/$B$8) -> 146.24665
B32: 0.08 | C32: =IF($B32<=C$30,0,(SUMPRODUCT($C$13:$G$13/(1+$B32)^$C$12:$G$12)+$G$13*(1+C$30)/($B32-C$30)/(1+$B32)^$G$12-$B$6+$B$7)/$B$8) -> 110.21363 | D32: =IF($B32<=D$30,0,(SUMPRODUCT($C$13:$G$13/(1+$B32)^$C$12:$G$12)+$G$13*(1+D$30)/($B32-D$30)/(1+$B32)^$G$12-$B$6+$B$7)/$B$8) -> 119.28805 | E32: =IF($B32<=E$30,0,(SUMPRODUCT($C$13:$G$13/(1+$B32)^$C$12:$G$12)+$G$13*(1+E$30)/($B32-E$30)/(1+$B32)^$G$12-$B$6+$B$7)/$B$8) -> 130.17736
B33: 0.085 | C33: =IF($B33<=C$30,0,(SUMPRODUCT($C$13:$G$13/(1+$B33)^$C$12:$G$12)+$G$13*(1+C$30)/($B33-C$30)/(1+$B33)^$G$12-$B$6+$B$7)/$B$8) -> 100.58674 | D33: =IF($B33<=D$30,0,(SUMPRODUCT($C$13:$G$13/(1+$B33)^$C$12:$G$12)+$G$13*(1+D$30)/($B33-D$30)/(1+$B33)^$G$12-$B$6+$B$7)/$B$8) -> 108.12453 | E33: =IF($B33<=E$30,0,(SUMPRODUCT($C$13:$G$13/(1+$B33)^$C$12:$G$12)+$G$13*(1+E$30)/($B33-E$30)/(1+$B33)^$G$12-$B$6+$B$7)/$B$8) -> 117.03284
B34: 0.09 | C34: =IF($B34<=C$30,0,(SUMPRODUCT($C$13:$G$13/(1+$B34)^$C$12:$G$12)+$G$13*(1+C$30)/($B34-C$30)/(1+$B34)^$G$12-$B$6+$B$7)/$B$8) -> 92.338166 | D34: =IF($B34<=D$30,0,(SUMPRODUCT($C$13:$G$13/(1+$B34)^$C$12:$G$12)+$G$13*(1+D$30)/($B34-D$30)/(1+$B34)^$G$12-$B$6+$B$7)/$B$8) -> 98.681399 | E34: =IF($B34<=E$30,0,(SUMPRODUCT($C$13:$G$13/(1+$B34)^$C$12:$G$12)+$G$13*(1+E$30)/($B34-E$30)/(1+$B34)^$G$12-$B$6+$B$7)/$B$8) -> 106.08184
B35: 0.095 | C35: =IF($B35<=C$30,0,(SUMPRODUCT($C$13:$G$13/(1+$B35)^$C$12:$G$12)+$G$13*(1+C$30)/($B35-C$30)/(1+$B35)^$G$12-$B$6+$B$7)/$B$8) -> 85.192185 | D35: =IF($B35<=D$30,0,(SUMPRODUCT($C$13:$G$13/(1+$B35)^$C$12:$G$12)+$G$13*(1+D$30)/($B35-D$30)/(1+$B35)^$G$12-$B$6+$B$7)/$B$8) -> 90.589929 | E35: =IF($B35<=E$30,0,(SUMPRODUCT($C$13:$G$13/(1+$B35)^$C$12:$G$12)+$G$13*(1+E$30)/($B35-E$30)/(1+$B35)^$G$12-$B$6+$B$7)/$B$8) -> 96.818094
B36: 0.1 | C36: =IF($B36<=C$30,0,(SUMPRODUCT($C$13:$G$13/(1+$B36)^$C$12:$G$12)+$G$13*(1+C$30)/($B36-C$30)/(1+$B36)^$G$12-$B$6+$B$7)/$B$8) -> 78.941999 | D36: =IF($B36<=D$30,0,(SUMPRODUCT($C$13:$G$13/(1+$B36)^$C$12:$G$12)+$G$13*(1+D$30)/($B36-D$30)/(1+$B36)^$G$12-$B$6+$B$7)/$B$8) -> 83.579735 | E36: =IF($B36<=E$30,0,(SUMPRODUCT($C$13:$G$13/(1+$B36)^$C$12:$G$12)+$G$13*(1+E$30)/($B36-E$30)/(1+$B36)^$G$12-$B$6+$B$7)/$B$8) -> 88.880004
A37: Each cell reruns the full DCF at that WACC and growth rate. Find the cell closest to your WACC and 2.5% for your base case.

Sheet Comps
A1: Peer Comparison (EV/EBITDA)
A2: Take every multiple, and Stantec's EBITDA, from ONE source (Yahoo Finance Statistics tab or stockanalysis.com) so definitions match.
A3: Company | B3: Ticker | C3: EV/EBITDA | D3: Notes
A4: WSP Global | B4: WSP (TSX) | C4: 13.52
A5: AECOM | B5: ACM (NYSE) | C5: 10.87
A6: Tetra Tech | B6: TTEK (NASDAQ) | C6: 14.06
A7: Jacobs | B7: J (NYSE) | C7: 21.45
A8: Peer median | C8: =IF(COUNT(C4:C7)=0,0,MEDIAN(C4:C7)) -> 13.79 | D8: Median, so one unusual company doesn't skew it
A10: Stantec | B10: STN | C10: 11.56
A11: Stantec premium / (discount) to peers | C11: =IF(OR(C8=0,C10=0),0,C10/C8-1) -> -0.16171139
A13: Stantec EBITDA, same source ($mm) | C13: 1030
A14: Implied enterprise value | C14: =C8*C13 -> 14203.7 | D14: peer median × Stantec EBITDA
A15: Less: debt | C15: =Historicals!D29 -> 1818.3
A16: Plus: cash | C16: =Historicals!D24 -> 398.1
A17: Implied equity value | C17: =IF(C14=0,0,C14-C15+C16) -> 12783.5
A18: Implied value per share (C$) | C18: =IF(Assumptions!B18=0,0,C17/Assumptions!B18) -> 112.03769

Sheet Summary
A1: Stantec Inc. (TSX/NYSE: STN) — Valuation Summary
A2: Prepared by: Muhammad Ahsan · October 2, 2026
A4: Valuation | B4: Value
A5: Current share price (C$) | B5: =DCF!B9 -> 96.25
A6: DCF value per share (C$) | B6: =DCF!B25 -> 137.99809
A7: Upside / (downside) | B7: =DCF!B27 -> 0.43374635
A8: Verdict | B8: =IF(OR(B5=0,B6=0),"Fill in market inputs",IF(B7>0.1,"Undervalued",IF(B7<-0.1,"Overvalued","Fairly valued"))) -> Undervalued | C8: Within ±10% of price = fairly valued
A9: Sensitivity range: low (C$) | B9: =MIN(DCF!C31:E36) -> 78.941999
A10: Sensitivity range: high (C$) | B10: =MAX(DCF!C31:E36) -> 146.24665
A11: Comps-implied value per share (C$) | B11: =Comps!C18 -> 112.03769
A13: Key assumptions | B13: Value
A14: Net revenue growth, 2026 → 2030 | B14: =TEXT(Assumptions!B4,"0%")&" → "&TEXT(Assumptions!F4,"0%") -> 10% → 5%
A15: Admin & marketing % of net revenue | B15: =Assumptions!B6 -> 0.375
A16: WACC | B16: =WACC!B18 -> 0.073261746
A17: Terminal growth | B17: =Assumptions!B15 -> 0.025
A19: Why it could be worth more
A20: • Backlog of $8.6 billion at Dec 31, 2025, about 13 months of work already signed.
A21: • Margins improving: admin & marketing fell from 39.0% to 37.8% of net revenue in 2025.
A22: • Strong cash conversion: 2025 operating cash flow of $862.9M vs. net income of $479.4M.
A23: • Modest debt: net debt to adjusted EBITDA of 1.3x, inside management's 1.0–2.0x range.
A25: Risks
A26: • About 52% of 2025 net revenue came from the US, so US spending and the exchange rate matter.
A27: • Growth relies partly on acquisitions (3.9 points of 2025's 10.7% growth), which must be integrated well.
A28: • Much of the work depends on public infrastructure budgets.
A30: Source for figures above: Stantec Q4 and full-year 2025 results release (Feb 25, 2026).
